Workbook

Sheet README
A1: README — what each tab does, who owns it, and how to fill it
A2: VSYST CEO Workbook · version 1.0 · built 2026-08-25 · companion to CEO-Docs. Grey italic on pale yellow = example data, overwrite it. Pale blue = a live formula, do not type over it. Pale green = a cell you are meant to type into. Import to Google Sheets: File → Import → Upload → Replace spreadsheet, then re-check the formulas on the Cap Table and Runway tabs.
A4: # | B4: Tab | C4: What it does | D4: Key formulas / how to fill | E4: Suggested owner · cadence
A5: 1 | B5: README | C5: This page: tab guide, colour legend, Google Sheets import note. | D5: Read the legend in the subtitle before touching anything. | E5: CEO · on every version bump
A6: 2 | B6: Strategy Kernel | C6: Rumelt's diagnosis / guiding policy / coherent action, plus the Playing-to-Win cascade and the assumption register that keeps the strategy honest. | D6: Free text. The Assumptions block scores confidence and forces a test date. Review quarterly; a change needs a Decision Journal row. | E6: CEO · quarterly (rewritten annually)
A7: 3 | B7: Market Map | C7: Bottom-up TAM / SAM / SOM for Indian fuel distribution, segment scoring, and penetration scenarios priced off the per-GSTIN metric. | D7: TAM = universe × GSTINs per firm × annual price. SOM rows drive off the penetration % you type. Every source number needs a citation and a VERIFY LIVE date. | E7: CEO · half-yearly
A8: 4 | B8: Unit Economics | C8: CAC, gross margin, payback, LTV and contribution per paying GSTIN, built from real VSYST cost lines. | D8: Everything below the input block is computed. Change only the green cells. CAC is founder time × day rate ÷ close rate. | E8: CEO with CA · quarterly
A9: 5 | B9: Runway & Scenarios | C9: 24-month cash projection in three cases (Base / Bear / Bull) plus the trigger ladder that pre-commits what happens at 12/9/6/3 months of runway. | D9: Pick the scenario in B6; the projection reads its drivers. Runway = closing cash ÷ trailing-3-month net burn. The COO workbook owns the weekly 13-week view; this one owns the scenario. | E9: CEO · monthly, and on any cash surprise
A10: 6 | B10: Cap Table & Dilution | C10: Current cap table plus a two-round dilution model (seed, Series A) with the pre- vs post-money ESOP pool switch. | D10: Type the round inputs in the green cells; ownership columns recompute. The pool-timing toggle in B30 is the single most expensive cell in this workbook. | E10: CEO with CS · on any change
A11: 7 | B11: ESOP Pool | C11: Pool size, grant register, vesting maths and the grant guideline by level. | D11: Vested = options × elapsed months ÷ total months, zero before the cliff. Strike and 11UA valuation date come from the CS. | E11: CEO with CS · on every grant
A12: 8 | B12: CEO Dashboard | C12: The CEO's monthly instrument panel — deliberately different from the COO's weekly KPI Scorecard: fewer rows, longer horizon, strategy and cash first. | D12: Fill one column per month. Status is computed from Direction, Goal and Red line. Read it before the board pack, not after. | E12: CEO · monthly by the 5th
A13: 9 | B13: Annual Plan & OKRs | C13: The year's theme and bet, 3–5 objectives with key results, owners, baselines, targets and confidence. | D13: % done = (current − baseline) ÷ (target − baseline). Confidence is typed, not computed — that is the point. | E13: CEO · set annually, scored quarterly
A14: 10 | B14: Decision Journal | C14: Every decision worth remembering: type, reversibility, options, reasoning, what would change your mind, and the outcome scored later. | D14: Verdict compares decision quality against outcome so you stop rewarding luck. Review the open rows every quarter. | E14: CEO · at the decision, reviewed quarterly
A15: 11 | B15: Board Calendar | C15: Board meeting dates with the statutory gap computed, plus the notice / pack / quorum / minutes trail and the director filings the CEO personally signs. | D15: Gap (days) is computed between consecutive meetings — watch the §173 limit. Dates and forms are VERIFY LIVE with the CS. | E15: CEO with CS · set in April, checked monthly
A16: 12 | B16: Pipeline | C16: The CEO's own founder-led sales pipeline — named dealers, districts, stage, next step, weighted value and the objection that is actually blocking. | D16: Weighted ₹ = potential × probability. The Next step / Next date pair is the only discipline that matters; a blank one is a dead deal. | E16: CEO · updated after every call
... A18: 14 | B18: Risk & Pre-Mortem | C18: The pre-mortem — it is 24 months from now and VSYST failed, why? — scored by likelihood × impact, with the early-warning signal and the owner. | D18: Score = Likelihood × Impact. Sort descending; the top three get a mitigation with a date. The COO workbook's Risk Register owns operational risk; this owns existential risk. | E18: CEO · quarterly, and after any near-miss
A20: Colour legend
B21: Example data — grey italic. Overwrite it; it is there to show the shape, and the numbers are illustrative only.
B22: Computed cell — a live formula. Do not type over it.
B23: Input cell — this is where you type.
B24: Section band — a heading inside the sheet.
A26: Honesty rule: every rupee figure, statutory date, threshold and market-size input in this workbook is illustrative or was true on 2026-08-25. Anything a real decision turns on is VERIFY LIVE — confirm with the CA, the CS or the source before acting on it.

Sheet Strategy Kernel
A1: Strategy Kernel — diagnosis, guiding policy, coherent action (Rumelt) + the Playing-to-Win cascade
A2: Fills C04 and C05. Rewritten annually, reviewed quarterly. A change to the diagnosis is a one-way door — log it in the Decision Journal. Example text is illustrative; argue with it, do not inherit it.
A4: A. The kernel
A5: Element | B5: Our answer (write it so it could be wrong) | C5: Why we believe it — evidence | D5: Confidence | E5: Set on | F5: Review on | G5: Owner
A6: Diagnosis — what is actually going on | B6: Indian fuel dealers do not lack software; they lack a reason to change a paper process that already works for them. The buyer is a busy owner with low software trust, a real switching cost in his ledger, and an accountant who prefers Tally. The binding constraint is adoption friction and district-level trust, not features. | C6: Field conversations; the affordability and education-gap research in docs/learning/company. | D6: 0.6 | E6: 46259 | F6: 46351 | G6: CEO
A7: Guiding policy — the approach that beats the constraint | B7: Win one district at a time by removing the dealer's single most painful reconciliation, and let dealer-to-dealer proof carry us to the next dealer. Sell trust, not features. Never make the dealer's ledger our experiment. | C7: Follows from the diagnosis; consistent with the per-GSTIN, web-only pricing decision. | D7: 0.6 | E7: 46259 | F7: 46351 | G7: CEO
A8: Coherent action 1 | B8: Founder-led sales in one district until 10 paying GSTINs, with a written script and objection bank (C10). | D8: 0.7 | E8: 46259 | F8: 46351 | G8: CEO
A9: Coherent action 2 | B9: Onboarding measured as time-to-first-invoice, not as a signup count. | D9: 0.7 | E9: 46259 | F9: 46351 | G9: CEO
A10: Coherent action 3 | B10: Ledger correctness treated as a company-level incident, above any feature. | D10: 0.8 | E10: 46259 | F10: 46351 | G10: CEO
A11: Coherent action 4 | B11: Annual prepay pricing per GSTIN on the web, funding the next district's travel. | D11: 0.5 | E11: 46259 | F11: 46351 | G11: CEO
A12: What we are deliberately NOT doing | B12: No pan-India launch, no free tier, no bespoke builds for one dealer, no in-app purchase, no OMC-scale pursuit that costs more than one founder-quarter. | D12: 0.7 | E12: 46259 | F12: 46351 | G12: CEO
A14: B. Playing to Win — the choice cascade (Lafley & Martin)
A15: Question | B15: Our choice | C15: What must be true for this to work | D15: Confidence | E15: Set on | F15: Review on | G15: Owner
A16: What is our winning aspiration? | B16: The default operating system for Indian fuel distribution, starting with Chhattisgarh. | D16: 0.6 | E16: 46259 | F16: 46351 | G16: CEO
A17: Where will we play? | B17: Petrol-pump dealers and bulk-diesel operators with ≥1 B2B credit customer, in Chhattisgarh districts first. Not lubricant-only distributors yet. Not pan-India. | D17: 0.6 | E17: 46259 | F17: 46351 | G17: CEO
A18: How will we win? | B18: Mobile-first for the dealer, GST-native, and the only system that holds the dealer↔customer rate confirmation and ledger in one auditable trail. | D18: 0.6 | E18: 46259 | F18: 46351 | G18: CEO
A19: What capabilities must be in place? | B19: Founder-led district selling; onboarding that reaches first invoice in days; ledger correctness; low-bandwidth Android quality; Hindi-first UX. | D19: 0.6 | E19: 46259 | F19: 46351 | G19: CEO
A20: What management systems are required? | B20: The COO course's operating system — cadence, scorecard, SOPs, compliance calendar — plus this workbook's CEO Dashboard and Decision Journal. | D20: 0.6 | E20: 46259 | F20: 46351 | G20: CEO
A22: C. Assumption register — what would prove the strategy wrong
A23: Assumption we are betting on | B23: If it is false, what breaks | C23: The smallest test | D23: Confidence | E23: Test by | F23: Tested on | G23: Verdict / what we learned
A24: A dealer will pay per GSTIN for this, annually, on a web page | B24: The whole revenue model; pricing metric and billing channel both | C24: Ask 10 qualified dealers for a signed annual order at list price | D24: 0.5 | E24: 46356
A25: The dealer's B2B customers will use the customer app | B25: Retention and the two-sided ledger asset; the moat argument | C25: Measure customer-side confirmations per active dealer for 60 days | D25: 0.45 | E25: 46356
A26: One district's dealers refer other dealers | B26: The whole go-to-market; CAC stays high without it | C26: Track referral source on every deal for two quarters | D26: 0.4 | E26: 46356
A27: Reconciliation pain is the top-3 pain for the owner, not the accountant | B27: The positioning and the demo order | C27: 10 switch interviews (C09), coded for stated pain rank | D27: 0.55 | E27: 46356
A28: We can onboard a dealer to first invoice in under 7 days without a founder on site | B28: Scalability past one district; the first sales hire's viability | C28: Onboard 3 dealers remotely and time it | D28: 0.35 | E28: 46356
A30: D. Strategy review log — a change here is a one-way door
A31: Date | B31: What changed | C31: The evidence that forced it | D31: Persist / pivot | E31: Decision Journal ID | F31: Board informed on | G31: Owner
A32: 46259 | B32: Kernel written for the first time | C32: Course lesson 05 exercise | D32: n/a | E32: DJ-001 | G32: CEO

Sheet Market Map
A1: Market Map — bottom-up TAM / SAM / SOM, segment scoring and penetration scenarios
A2: Fills C06. Every universe count below is an INPUT you must source and date — replace the illustrative figures and cite PPAC / MoPNG / OMC disclosures. VERIFY LIVE before any of this reaches a deck or a board pack.
A4: A. Pricing inputs (from the per-GSTIN decision — see C11)
A5: Input | B5: Value | C5: Unit | G5: Source / note
A6: List price per GSTIN per month | B6: 1799 | C6: ₹ | G6: Matches C11 and lessons 05/08. VERIFY LIVE.
A7: Annual price per GSTIN | B7: =B6*12 | C7: ₹ | G7: Annual prepay is the default plan
A8: Average GSTINs per dealer firm | B8: 1.3 | C8: count | G8: Multi-GSTIN dealers are the upside. Illustrative.
A9: Average annual revenue per firm (ARPA) | B9: =B7*B8 | C9: ₹ | G9: Drives every number below
A11: B. The universe — replace every figure and cite it
A12: Universe | B12: Count | C12: Source | D12: As of | E12: Addressable % | F12: Addressable count | G12: Why this filter
A13: Retail fuel outlets in India (all OMCs) | B13: 90000 | C13: PPAC / OMC disclosures — VERIFY LIVE | D13: 2026 | E13: 0.15 | F13: =B13*E13 | G13: Dealers with ≥1 B2B credit customer and enough volume to feel reconciliation pain
A14: Retail fuel outlets in Chhattisgarh | B14: 1400 | C14: State OMC data — VERIFY LIVE | D14: 2026 | E14: 0.25 | F14: =B14*E14 | G14: Home state; founder can reach them physically
A15: Bulk diesel / doorstep delivery operators (India) | B15: 6000 | C15: MoPNG / industry press — VERIFY LIVE | D15: 2026 | E15: 0.3 | F15: =B15*E15 | G15: B2B by definition; highest reconciliation pain
A16: Lubricant distributors (India) | B16: 12000 | C16: Industry estimate — VERIFY LIVE | D16: 2026 | E16: 0.1 | F16: =B16*E16 | G16: Different workflow; a later segment, not now
A18: C. TAM / SAM / SOM
A19: Layer | B19: Firms | C19: Basis | F19: Annual ₹ | G19: What it means
A20: TAM — every fuel retail outlet in India | B20: =B13 | C20: Total universe, all outlets | F20: =B20*$B$9 | G20: The number for a deck, not for a plan
A21: SAM — India outlets that fit the ICP | B21: =F13+F15 | C21: Addressable outlets + bulk operators | F21: =B21*$B$9 | G21: Who we could sell to with today's product
A22: SOM — Chhattisgarh, addressable | B22: =F14 | C22: Home-state addressable outlets | F22: =B22*$B$9 | G22: The only number the next 18 months are about
A24: D. Penetration scenarios against SOM
A25: Scenario | B25: Penetration of SOM | C25: Paying firms | D25: Paying GSTINs | E25: Annual ₹ | F25: Monthly ₹ | G25: What it takes
A26: Toehold | B26: 0.01 | C26: =ROUND($B$22*B26,0) | D26: =ROUND(C26*$B$8,0) | E26: =C26*$B$9 | F26: =E26/12 | G26: One district, founder-led
A27: Beachhead | B27: 0.03 | C27: =ROUND($B$22*B27,0) | D27: =ROUND(C27*$B$8,0) | E27: =C27*$B$9 | F27: =E27/12 | G27: Three districts, one sales hire
A28: Home-state leader | B28: 0.1 | C28: =ROUND($B$22*B28,0) | D28: =ROUND(C28*$B$8,0) | E28: =C28*$B$9 | F28: =E28/12 | G28: Statewide, a real sales team and support function
A29: Default alive | B29: 0.05 | C29: =ROUND($B$22*B29,0) | D29: =ROUND(C29*$B$8,0) | E29: =C29*$B$9 | F29: =E29/12 | G29: Whatever penetration covers total costs — solve for it
A31: E. Segments — score before you choose
A32: Segment | B32: Pain intensity 1-5 | C32: Ability to pay 1-5 | D32: Reachability 1-5 | E32: Product fit today 1-5 | F32: Score (product) | G32: Verdict
A33: Petrol-pump dealer with B2B credit book | B33: 5 | C33: 4 | D33: 4 | E33: 5 | F33: =B33*C33*D33*E33 | G33: Primary — this is where to play
A34: Bulk diesel / doorstep delivery operator | B34: 5 | C34: 4 | D34: 3 | E34: 4 | F34: =B34*C34*D34*E34 | G34: Secondary — same pain, harder to reach
A35: Petrol-pump dealer, retail-only, no credit customers | B35: 2 | C35: 3 | D35: 4 | E35: 2 | F35: =B35*C35*D35*E35 | G35: Disqualify — no reconciliation pain to sell against
A36: Lubricant distributor | B36: 3 | C36: 3 | D36: 2 | E36: 2 | F36: =B36*C36*D36*E36 | G36: Later — different workflow, needs product work
A37: Fleet / transporter (the dealer's customer) | B37: 4 | C37: 3 | D37: 2 | E37: 3 | F37: =B37*C37*D37*E37 | G37: Not a buyer — rides free on the dealer's tenant by design
A39: F. The real alternatives (what we are actually replacing)
A40: Alternative | B40: What it costs the dealer today | C40: Why he keeps it | D40: Where it fails him | E40: Our wedge | F40: Threat 1-5 | G40: Note
A41: Paper Daily Sales Register | B41: Hours per day; variance found at month end | C41: It has never failed him; his staff know it | D41: No credit visibility, no dispute trail | E41: The rate-confirmation trail | F41: 5
A42: Tally + the accountant | B42: Annual licence + accountant fees | C42: GST filings depend on it | D42: Nothing operational; days behind reality | E42: We feed Tally, we don't fight it | F42: 4
A43: WhatsApp for orders and rates | B43: Free | C43: Every customer already has it | D43: No record, endless rate disputes | E43: Confirmed rates with a timestamp | F43: 5
A44: Excel credit tracker | B44: Free | C44: He built it himself | D44: Breaks past ~30 customers; one file, one person | E44: Multi-user ledger with lineage | F44: 3
A45: Another billing app / ATG vendor software | B45: ₹ varies | C45: Bundled with hardware | D45: Not built for the B2B credit workflow | E45: Two-sided, dealer↔customer | F45: 3

Sheet Unit Economics
A1: Unit Economics — CAC, gross margin, payback, LTV and contribution per paying GSTIN
A2: Fills C12. Green cells are inputs; blue cells compute. At pre-revenue every figure here is a hypothesis — write the date you last tested each one. LTV/CAC is the least trustworthy number on this sheet; payback is the most.
A4: A. Revenue inputs
A5: Input | B5: Value | C5: Unit | D5: How to get it honestly
A6: Price per GSTIN per month | B6: 1799 | C6: ₹ | D6: From C11. Use list price, not the discounted one.
A7: GSTINs per paying firm | B7: 1.3 | C7: count | D7: Actual average across signed dealers.
A8: Monthly revenue per firm (ARPA) | B8: =B6*B7 | C8: ₹ | D8: Computed.
A9: Annual revenue per firm | B9: =B8*12 | C9: ₹ | D9: Computed.
A11: B. Cost to serve one dealer tenant, per month
A12: Cost line | B12: ₹ / tenant / month | C12: Basis | D12: Note
A13: AWS compute + storage + bandwidth | B13: 120 | C13: Total AWS ÷ active tenants | D13: Falls with scale; re-measure every quarter
A14: MongoDB Atlas | B14: 90 | C14: Cluster cost ÷ active tenants | D14: Watch the per-tenant document growth
A15: SMS / OTP (2Factor) — driver + rate confirmations | B15: 210 | C15: Messages × rate | D15: Scales with the dealer's transaction volume, not with headcount
A16: Push notifications / Firebase | B16: 15 | C16: Flat
A17: Payment gateway fees on subscription collection | B17: 40 | C17: ≈1.7% of ARPA | D17: Easebuzz rate; price-derived — recompute if C11 price changes. VERIFY LIVE
A18: Support cost (human minutes) | B18: 400 | C18: Support hours × loaded cost ÷ tenants | D18: The one that decides whether this business scales
A19: Onboarding amortised over 24 months | B19: 250 | C19: Onboarding cost ÷ 24 | D19: Move to CAC instead if you prefer; be consistent
A20: Total cost to serve, per tenant per month | B20: =SUM(B13:B19) | D20: Computed
A21: Gross margin per tenant per month | B21: =B8-B20 | D21: Computed
A22: Gross margin % | B22: =IF(B8=0,"",B21/B8) | D22: SaaS benchmark is 70–80%+. Below 60% means support or SMS is eating the business.
A24: C. Cost to acquire one dealer (founder-led, district by district)
A25: Input | B25: Value | C25: Unit | D25: How to get it honestly
A26: Founder days spent per closed deal | B26: 6 | C26: days | D26: Count travel, demos, follow-ups and the paperwork. Be honest.
A27: Loaded cost of a founder day | B27: 4000 | C27: ₹ | D27: Salary ÷ working days. Use the real number even if you don't pay yourself yet — it is a real cost.
A28: Travel + hospitality per deal | B28: 3500 | C28: ₹ | D28: Fuel, stay, food, the dealer's tea.
A29: Marketing / collateral per deal | B29: 500 | C29: ₹ | D29: Printing, demo device, association fees amortised.
A30: Deals closed ÷ qualified conversations | B30: 0.2 | C30: ratio | D30: The honest close rate, counted over 20+ conversations.
A31: CAC per closed dealer | B31: =(B26*B27+B28+B29)/B30 | C31: ₹ | D31: Founder time is the dominant term. If this frightens you, that is the correct reaction — it is why lesson 07 insists on a script.
A33: D. The four numbers that decide the business
A34: Metric | B34: Value | C34: Target | D34: Reading
A35: Gross margin % | B35: =B22 | C35: 0.75 | D35: Below target → attack SMS cost and support minutes before attacking price.
A36: CAC payback (months) | B36: =IF(B21<=0,"never",B31/B21) | C36: 12 | D36: Months of gross margin to repay acquisition. Under 12 is healthy for SMB SaaS; over 24 means the motion is wrong, not the price.
A37: Monthly logo churn % | B37: 0.02 | C37: 0.015 | D37: Typed, from actuals. Anything above 3%/month makes LTV meaningless.
A38: Expected lifetime (months) | B38: =IF(B37=0,"",1/B37) | D38: 1 ÷ monthly churn.
A39: LTV (gross margin basis) | B39: =B21*B38 | D39: Gross margin, never revenue. Revenue-based LTV is a lie you tell yourself.
A40: LTV ÷ CAC | B40: =IF(B31=0,"",B39/B31) | C40: 3 | D40: Rule of thumb only. With fewer than ~30 customers this ratio is noise — trust payback instead.
A41: Paying firms needed to cover total monthly costs | B41: =IF(B21<=0,"never",ROUNDUP(150000/B21,0)) | D41: Replace 150000 with this month's total operating cost from Runway & Scenarios. This is the 'default alive' number.

Sheet Runway & Scenarios
A1: Runway & Scenarios — 24-month cash in three cases, and the trigger ladder
A2: Fills C13. The COO workbook owns the weekly 13-week cash view; this sheet owns the scenario and the pre-committed trigger. Change the scenario in B5 and the whole projection re-reads its drivers. Figures illustrative — VERIFY LIVE against the bank.
A4: A. Scenario switch and drivers
A5: Active scenario → | B5: Base | C5: Type Base, Bear or Bull. Everything below reads this cell.
A7: Driver | B7: Bear | C7: Base | D7: Bull | E7: Active | I7: How to set it honestly
A8: Opening cash today (₹) | B8: 2500000 | C8: 2500000 | D8: 2500000 | E8: =IF($B$5="Bear",B8,IF($B$5="Bull",D8,C8)) | I8: Bank + FD + anything liquid, today. One number, no optimism.
A9: New paying firms per month | B9: 0.5 | C9: 1.5 | D9: 3 | E9: =IF($B$5="Bear",B9,IF($B$5="Bull",D9,C9)) | I9: Your actual close rate × conversations you can physically hold.
A10: Annual revenue per firm (₹) | B10: 21588 | C10: 28065 | D10: 32382 | E10: =IF($B$5="Bear",B10,IF($B$5="Bull",D10,C10)) | I10: From Unit Economics B9 (1799 x 12 x GSTINs/firm).
A11: Monthly logo churn | B11: 0.04 | C11: 0.02 | D11: 0.01 | E11: =IF($B$5="Bear",B11,IF($B$5="Bull",D11,C11)) | I11: From actuals once you have any.
A12: Fixed monthly costs (₹) | B12: 190000 | C12: 165000 | D12: 165000 | E12: =IF($B$5="Bear",B12,IF($B$5="Bull",D12,C12)) | I12: Salaries, cloud, tools, CA/CS, rent. The bear case is higher because problems cost money.
A13: Variable cost per firm per month (₹) | B13: 1400 | C13: 1125 | D13: 900 | E13: =IF($B$5="Bear",B13,IF($B$5="Bull",D13,C13)) | I13: Base = C12 §B cost to serve (₹1,125). Bear/bull are scenario assumptions.
A14: Hiring: month of first hire | B14: 99 | C14: 12 | D14: 8 | E14: =IF($B$5="Bear",B14,IF($B$5="Bull",D14,C14)) | I14: 99 = not in this scenario.
A15: Hiring: added monthly cost (₹) | B15: 0 | C15: 45000 | D15: 60000 | E15: =IF($B$5="Bear",B15,IF($B$5="Bull",D15,C15)) | I15: Fully loaded, including PF/ESI where applicable.
A17: B. The floor — cash that is not spendable (C13 rule 11)
A18: Reserve | B18: ₹ | I18: How to set it honestly
A19: Operating reserve | B19: 300000 | I19: One bad month is not an emergency. Roughly two months of fixed cost.
A20: Exit reserve — ring-fenced, not spendable | B20: 450000 | I20: What it would cost to end the company properly, today: closing accounts, strike-off (STK-2 via C-PACE) or IBC s.59, unexpired prepayments refunded, vendor and settlement dues, full-and-final for anyone employed, per-tenant data export and verified deletion under DPDP s.8, plus a 25% buffer. Drivers in lesson 18 §10.6. VERIFY LIVE with the CA and the CS — re-price at the annual plan, after every hire, and on signing any annual prepayment.
A21: Total floor | B21: =B19+B20 | I21: Column I below reads runway net of the exit reserve. The 3-month rung may not spend it.
A22: Month closing cash first falls below the floor | B22: =IF(COUNTIF(H26:H49,"<"&B21)=0,"never within 24 months",SUMPRODUCT(MIN((H26:H49<B21)*A26:A49+(H26:H49>=B21)*9999))) | I22: If this lands inside 24 months, the ladder is not theoretical. Read it with section D.
A24: C. 24-month projection (reads the active column)
A25: Month # | B25: Paying firms | C25: Revenue ₹ | D25: Fixed cost ₹ | E25: Variable cost ₹ | F25: Total cost ₹ | G25: Net ₹ | H25: Closing cash ₹ | I25: Runway (months, net of exit reserve)
A26: 1 | B26: =$E$9 | C26: =B26*$E$10/12 | D26: =$E$12+IF(1>=$E$14,$E$15,0) | E26: =B26*$E$13 | F26: =D26+E26 | G26: =C26-F26 | H26: =$E$8+G26 | I26: =IF(AVERAGE(G26:G26)>=0,"n/a — cash positive",IF(H26-$B$20<=0,0,(H26-$B$20)/-AVERAGE(G26:G26)))
A27: 2 | B27: =MAX(0,B26*(1-$E$11)+$E$9) | C27: =B27*$E$10/12 | D27: =$E$12+IF(2>=$E$14,$E$15,0) | E27: =B27*$E$13 | F27: =D27+E27 | G27: =C27-F27 | H27: =H26+G27 | I27: =IF(AVERAGE(G26:G27)>=0,"n/a — cash positive",IF(H27-$B$20<=0,0,(H27-$B$20)/-AVERAGE(G26:G27)))
A28: 3 | B28: =MAX(0,B27*(1-$E$11)+$E$9) | C28: =B28*$E$10/12 | D28: =$E$12+IF(3>=$E$14,$E$15,0) | E28: =B28*$E$13 | F28: =D28+E28 | G28: =C28-F28 | H28: =H27+G28 | I28: =IF(AVERAGE(G26:G28)>=0,"n/a — cash positive",IF(H28-$B$20<=0,0,(H28-$B$20)/-AVERAGE(G26:G28)))
A29: 4 | B29: =MAX(0,B28*(1-$E$11)+$E$9) | C29: =B29*$E$10/12 | D29: =$E$12+IF(4>=$E$14,$E$15,0) | E29: =B29*$E$13 | F29: =D29+E29 | G29: =C29-F29 | H29: =H28+G29 | I29: =IF(AVERAGE(G27:G29)>=0,"n/a — cash positive",IF(H29-$B$20<=0,0,(H29-$B$20)/-AVERAGE(G27:G29)))
A30: 5 | B30: =MAX(0,B29*(1-$E$11)+$E$9) | C30: =B30*$E$10/12 | D30: =$E$12+IF(5>=$E$14,$E$15,0) | E30: =B30*$E$13 | F30: =D30+E30 | G30: =C30-F30 | H30: =H29+G30 | I30: =IF(AVERAGE(G28:G30)>=0,"n/a — cash positive",IF(H30-$B$20<=0,0,(H30-$B$20)/-AVERAGE(G28:G30)))
A31: 6 | B31: =MAX(0,B30*(1-$E$11)+$E$9) | C31: =B31*$E$10/12 | D31: =$E$12+IF(6>=$E$14,$E$15,0) | E31: =B31*$E$13 | F31: =D31+E31 | G31: =C31-F31 | H31: =H30+G31 | I31: =IF(AVERAGE(G29:G31)>=0,"n/a — cash positive",IF(H31-$B$20<=0,0,(H31-$B$20)/-AVERAGE(G29:G31)))
A32: 7 | B32: =MAX(0,B31*(1-$E$11)+$E$9) | C32: =B32*$E$10/12 | D32: =$E$12+IF(7>=$E$14,$E$15,0) | E32: =B32*$E$13 | F32: =D32+E32 | G32: =C32-F32 | H32: =H31+G32 | I32: =IF(AVERAGE(G30:G32)>=0,"n/a — cash positive",IF(H32-$B$20<=0,0,(H32-$B$20)/-AVERAGE(G30:G32)))
A33: 8 | B33: =MAX(0,B32*(1-$E$11)+$E$9) | C33: =B33*$E$10/12 | D33: =$E$12+IF(8>=$E$14,$E$15,0) | E33: =B33*$E$13 | F33: =D33+E33 | G33: =C33-F33 | H33: =H32+G33 | I33: =IF(AVERAGE(G31:G33)>=0,"n/a — cash positive",IF(H33-$B$20<=0,0,(H33-$B$20)/-AVERAGE(G31:G33)))
A34: 9 | B34: =MAX(0,B33*(1-$E$11)+$E$9) | C34: =B34*$E$10/12 | D34: =$E$12+IF(9>=$E$14,$E$15,0) | E34: =B34*$E$13 | F34: =D34+E34 | G34: =C34-F34 | H34: =H33+G34 | I34: =IF(AVERAGE(G32:G34)>=0,"n/a — cash positive",IF(H34-$B$20<=0,0,(H34-$B$20)/-AVERAGE(G32:G34)))
A35: 10 | B35: =MAX(0,B34*(1-$E$11)+$E$9) | C35: =B35*$E$10/12 | D35: =$E$12+IF(10>=$E$14,$E$15,0) | E35: =B35*$E$13 | F35: =D35+E35 | G35: =C35-F35 | H35: =H34+G35 | I35: =IF(AVERAGE(G33:G35)>=0,"n/a — cash positive",IF(H35-$B$20<=0,0,(H35-$B$20)/-AVERAGE(G33:G35)))
A36: 11 | B36: =MAX(0,B35*(1-$E$11)+$E$9) | C36: =B36*$E$10/12 | D36: =$E$12+IF(11>=$E$14,$E$15,0) | E36: =B36*$E$13 | F36: =D36+E36 | G36: =C36-F36 | H36: =H35+G36 | I36: =IF(AVERAGE(G34:G36)>=0,"n/a — cash positive",IF(H36-$B$20<=0,0,(H36-$B$20)/-AVERAGE(G34:G36)))
A37: 12 | B37: =MAX(0,B36*(1-$E$11)+$E$9) | C37: =B37*$E$10/12 | D37: =$E$12+IF(12>=$E$14,$E$15,0) | E37: =B37*$E$13 | F37: =D37+E37 | G37: =C37-F37 | H37: =H36+G37 | I37: =IF(AVERAGE(G35:G37)>=0,"n/a — cash positive",IF(H37-$B$20<=0,0,(H37-$B$20)/-AVERAGE(G35:G37)))
A38: 13 | B38: =MAX(0,B37*(1-$E$11)+$E$9) | C38: =B38*$E$10/12 | D38: =$E$12+IF(13>=$E$14,$E$15,0) | E38: =B38*$E$13 | F38: =D38+E38 | G38: =C38-F38 | H38: =H37+G38 | I38: =IF(AVERAGE(G36:G38)>=0,"n/a — cash positive",IF(H38-$B$20<=0,0,(H38-$B$20)/-AVERAGE(G36:G38)))
A39: 14 | B39: =MAX(0,B38*(1-$E$11)+$E$9) | C39: =B39*$E$10/12 | D39: =$E$12+IF(14>=$E$14,$E$15,0) | E39: =B39*$E$13 | F39: =D39+E39 | G39: =C39-F39 | H39: =H38+G39 | I39: =IF(AVERAGE(G37:G39)>=0,"n/a — cash positive",IF(H39-$B$20<=0,0,(H39-$B$20)/-AVERAGE(G37:G39)))
A40: 15 | B40: =MAX(0,B39*(1-$E$11)+$E$9) | C40: =B40*$E$10/12 | D40: =$E$12+IF(15>=$E$14,$E$15,0) | E40: =B40*$E$13 | F40: =D40+E40 | G40: =C40-F40 | H40: =H39+G40 | I40: =IF(AVERAGE(G38:G40)>=0,"n/a — cash positive",IF(H40-$B$20<=0,0,(H40-$B$20)/-AVERAGE(G38:G40)))
A41: 16 | B41: =MAX(0,B40*(1-$E$11)+$E$9) | C41: =B41*$E$10/12 | D41: =$E$12+IF(16>=$E$14,$E$15,0) | E41: =B41*$E$13 | F41: =D41+E41 | G41: =C41-F41 | H41: =H40+G41 | I41: =IF(AVERAGE(G39:G41)>=0,"n/a — cash positive",IF(H41-$B$20<=0,0,(H41-$B$20)/-AVERAGE(G39:G41)))
A42: 17 | B42: =MAX(0,B41*(1-$E$11)+$E$9) | C42: =B42*$E$10/12 | D42: =$E$12+IF(17>=$E$14,$E$15,0) | E42: =B42*$E$13 | F42: =D42+E42 | G42: =C42-F42 | H42: =H41+G42 | I42: =IF(AVERAGE(G40:G42)>=0,"n/a — cash positive",IF(H42-$B$20<=0,0,(H42-$B$20)/-AVERAGE(G40:G42)))
A43: 18 | B43: =MAX(0,B42*(1-$E$11)+$E$9) | C43: =B43*$E$10/12 | D43: =$E$12+IF(18>=$E$14,$E$15,0) | E43: =B43*$E$13 | F43: =D43+E43 | G43: =C43-F43 | H43: =H42+G43 | I43: =IF(AVERAGE(G41:G43)>=0,"n/a — cash positive",IF(H43-$B$20<=0,0,(H43-$B$20)/-AVERAGE(G41:G43)))
A44: 19 | B44: =MAX(0,B43*(1-$E$11)+$E$9) | C44: =B44*$E$10/12 | D44: =$E$12+IF(19>=$E$14,$E$15,0) | E44: =B44*$E$13 | F44: =D44+E44 | G44: =C44-F44 | H44: =H43+G44 | I44: =IF(AVERAGE(G42:G44)>=0,"n/a — cash positive",IF(H44-$B$20<=0,0,(H44-$B$20)/-AVERAGE(G42:G44)))
A45: 20 | B45: =MAX(0,B44*(1-$E$11)+$E$9) | C45: =B45*$E$10/12 | D45: =$E$12+IF(20>=$E$14,$E$15,0) | E45: =B45*$E$13 | F45: =D45+E45 | G45: =C45-F45 | H45: =H44+G45 | I45: =IF(AVERAGE(G43:G45)>=0,"n/a — cash positive",IF(H45-$B$20<=0,0,(H45-$B$20)/-AVERAGE(G43:G45)))
A46: 21 | B46: =MAX(0,B45*(1-$E$11)+$E$9) | C46: =B46*$E$10/12 | D46: =$E$12+IF(21>=$E$14,$E$15,0) | E46: =B46*$E$13 | F46: =D46+E46 | G46: =C46-F46 | H46: =H45+G46 | I46: =IF(AVERAGE(G44:G46)>=0,"n/a — cash positive",IF(H46-$B$20<=0,0,(H46-$B$20)/-AVERAGE(G44:G46)))
A47: 22 | B47: =MAX(0,B46*(1-$E$11)+$E$9) | C47: =B47*$E$10/12 | D47: =$E$12+IF(22>=$E$14,$E$15,0) | E47: =B47*$E$13 | F47: =D47+E47 | G47: =C47-F47 | H47: =H46+G47 | I47: =IF(AVERAGE(G45:G47)>=0,"n/a — cash positive",IF(H47-$B$20<=0,0,(H47-$B$20)/-AVERAGE(G45:G47)))
A48: 23 | B48: =MAX(0,B47*(1-$E$11)+$E$9) | C48: =B48*$E$10/12 | D48: =$E$12+IF(23>=$E$14,$E$15,0) | E48: =B48*$E$13 | F48: =D48+E48 | G48: =C48-F48 | H48: =H47+G48 | I48: =IF(AVERAGE(G46:G48)>=0,"n/a — cash positive",IF(H48-$B$20<=0,0,(H48-$B$20)/-AVERAGE(G46:G48)))
A49: 24 | B49: =MAX(0,B48*(1-$E$11)+$E$9) | C49: =B49*$E$10/12 | D49: =$E$12+IF(24>=$E$14,$E$15,0) | E49: =B49*$E$13 | F49: =D49+E49 | G49: =C49-F49 | H49: =H48+G49 | I49: =IF(AVERAGE(G47:G49)>=0,"n/a — cash positive",IF(H49-$B$20<=0,0,(H49-$B$20)/-AVERAGE(G47:G49)))
A51: D. The trigger ladder — decided now, in the calm, not later in the panic
A52: Runway remaining | B52: Status | C52: What the CEO is obliged to do — no discretion | I52: Who must be told
A53: 12 months | B53: Green | C53: Normal operations. Review this ladder monthly and confirm the cash figure against the bank statement personally. | I53: Board / advisors at the quarterly
A54: 9 months | B54: Amber | C54: Write the plan you would execute at 6 months, and name the date you would start it. Freeze any new recurring cost above ₹10,000/month. Start the funding conversation you have been postponing (grants, prepay push, or investors). | I54: Co-founders, same week
A55: 6 months | B55: Red | C55: Execute the 9-month plan. Cut discretionary spend to zero. Convert every willing customer to annual prepay at a discount. Stop all work not on the shortest path to revenue. If raising, the process must already be running. | I55: Co-founders same day; board within a week
A56: 3 months | B56: Critical | C56: Founder salaries to statutory minimum or zero. The exit reserve is NOT available to this rung — spending it converts a company that can still stop well into one that can only stop badly. Talk to the CA about statutory dues sequencing so nothing becomes personal liability. Have the honest conversation with the team before they hear it elsewhere. Decide, in writing, the date on which you would stop. | I56: Everyone, immediately
A57: Cash-flow positive | B57: Earned | C57: Rebuild to 12 months of runway before adding any recurring cost. Then, and only then, spend on growth. | I57: Board at the next meeting

Sheet Cap Table & Dilution
A1: Cap Table & Dilution — the current table and a two-round model
A2: Fills C16. Illustrative shares and valuations. Every real change goes through the CS and the statutory registers — this sheet is a model, never the record. The pool-timing cell is the most expensive single input on it.
A4: A. Cap table today
A5: Holder | B5: Class | C5: Shares | D5: % fully diluted | I5: Note
A6: Founder-Director 1 (CEO) | B6: Equity | C6: 400000 | D6: =IF($C$10=0,"",C6/$C$10) | I6: Founder shares should be subject to a vesting / buy-back arrangement — see C02 and the CS.
A7: Founder-Director 2 (domain) | B7: Equity | C7: 300000 | D7: =IF($C$10=0,"",C7/$C$10) | I7: Founder shares should be subject to a vesting / buy-back arrangement — see C02 and the CS.
A8: Founder-Director 3 | B8: Equity | C8: 300000 | D8: =IF($C$10=0,"",C8/$C$10) | I8: Founder shares should be subject to a vesting / buy-back arrangement — see C02 and the CS.
A9: ESOP pool (unallocated) | B9: Reserved | C9: 0 | D9: =IF($C$10=0,"",C9/$C$10) | I9: Founder shares should be subject to a vesting / buy-back arrangement — see C02 and the CS.
A10: Total | C10: =SUM(C6:C9) | D10: =SUM(D6:D9)
A12: B. Round model — inputs
A13: Input | B13: Seed | C13: Series A | I13: Note
A14: Pre-money valuation (₹) | B14: 60000000 | C14: 300000000 | I14: The number everyone argues about and that matters less than the terms below.
A15: Amount raised (₹) | B15: 15000000 | C15: 60000000
A16: Target ESOP pool after the round | B16: 0.1 | C16: 0.12 | I16: The pool is topped up to this % of post-money.
A17: Pool created PRE-money? (1 = yes) | B17: 1 | C17: 1 | I17: 1 = founders alone bear the pool dilution (the market standard, and the expensive one). 0 = everyone shares it. Read lesson 08 §12 before typing here.
A18: Liquidation preference (x) | B18: 1 | C18: 1 | I18: 1x non-participating is the founder-friendly norm in India. VERIFY in the term sheet.
A19: Participating? (1 = yes) | B19: 0 | C19: 0 | I19: Participating preference double-dips on exit. Push back hard.
A21: C. Round model — computed outcome
A22: Output | B22: Seed | C22: Series A | I22: Reading
A23: Post-money valuation (₹) | B23: =B14+B15 | C23: =C14+C15 | I23: Post = pre + amount. Nothing subtle here.
A24: Investor ownership after round | B24: =B15/B23 | C24: =C15/C23 | I24: What the money buys.
A25: ESOP pool after round | B25: =B16 | C25: =C16 | I25: Target pool as a share of post-money.
A26: Everyone else (founders + prior investors) | B26: =1-B24-B25 | C26: =1-C24-C25 | I26: The residual. This is the number to watch across rounds.
A27: Effective price per share vs founders' cost | I27: Ask the CS — needs the share count and Rule 11UA valuation.
A28: Founder group ownership after Seed | B28: =B26 | I28: Assumes no prior outside holders.
A29: Founder group ownership after Series A | B29: =B28*C26 | I29: Compounding dilution — this is the number founders consistently under-estimate.
A30: Investor's minimum exit for a 1x return (₹) | B30: =B15*B18 | C30: =C15*C18 | I30: Below this, common shareholders may see nothing.
A31: Pool dilution borne by founders alone? | B31: =IF(B17=1,"Yes — founders pay for the pool","No — shared with the new investor") | C31: =IF(C17=1,"Yes — founders pay for the pool","No — shared with the new investor") | I31: On a ₹6 Cr pre-money, a 10% pre-money pool costs the founders roughly ₹60 lakh of value. It is a negotiable term.
A33: D. Terms that matter more than the valuation — fill from the actual term sheet
A34: Term | B34: What was offered | C34: Founder-friendly benchmark | D34: Accept / negotiate / refuse | I34: Why it matters
A35: Liquidation preference | C35: 1x non-participating | I35: Decides who gets paid first, and how much, on any exit.
A36: Anti-dilution | C36: Broad-based weighted average | I36: Full ratchet transfers the whole cost of a down round to founders.
A37: Board composition | C37: Founder majority at seed | I37: This is the term that decides whether you can be fired.
A38: Reserved matters / protective provisions | C38: Short list, high thresholds | I38: A long list means you need consent to run your own company.
A39: ESOP pool and its timing | C39: Post-money, or shared | I39: See row above — real money.
A40: Founder vesting reset | C40: Credit for time already served | I40: Refusing all credit for four years of work is a red flag about the investor.
A41: Drag-along | C41: Triggered by a real majority incl. founders | I41: Can force you to sell.
A42: Information rights | C42: Quarterly, standard | I42: Fine. Monthly audited is not.
A43: Exclusivity / no-shop | C43: 30–45 days | I43: Long exclusivity with a slow investor kills your leverage.
A44: Tag-along / ROFR | C44: Standard | I44: Governs secondary sales.

Sheet ESOP Pool
A1: ESOP Pool — pool size, grant register and vesting
A2: Fills C20. Grants for an Indian private company run under the Companies (Share Capital and Debentures) Rules, 2014 and need a board and shareholder resolution — the CS drives it, this sheet only tracks it. Strike price and valuation date: VERIFY LIVE with the CS. Perquisite tax on exercise applies — see lesson 10 §8.
A4: A. Pool
A5: Item | B5: Value | I5: Note
A6: Pool size (% fully diluted) | B6: 0.07 | I6: 7% — matches C20 and lesson 10. 10% is the seed-stage norm; revisit at the round. VERIFY LIVE.
A7: Pool size (options) | B7: 75269 | I7: From the cap table.
A8: Granted to date | B8: =SUM(D14:D30) | I8: Computed from the register below.
A9: Available to grant | B9: =B7-B8 | I9: Keep at least 40% of the pool for the next 18 months of hiring.
A11: B. Grant register
A13: Grantee | B13: Role / level | C13: Grant date | D13: Options | E13: Strike ₹ | F13: Vest start | G13: Cliff (months) | H13: Total (months) | I13: Vested today (computed)
A14: A. Example | B14: Senior Engineer / L5 | C14: 46296 | D14: 6000 | E14: 10 | F14: 46296 | G14: 12 | H14: 48 | I14: =IF(TODAY()<EDATE(F14,G14),0,MIN(D14,ROUND(D14*DATEDIF(F14,TODAY(),"m")/H14,0)))
G15: 12 | H15: 48 | I15: =IF(OR(D15="",F15=""),"",IF(TODAY()<EDATE(F15,G15),0,MIN(D15,ROUND(D15*DATEDIF(F15,TODAY(),"m")/H15,0))))
G16: 12 | H16: 48 | I16: =IF(OR(D16="",F16=""),"",IF(TODAY()<EDATE(F16,G16),0,MIN(D16,ROUND(D16*DATEDIF(F16,TODAY(),"m")/H16,0))))
G17: 12 | H17: 48 | I17: =IF(OR(D17="",F17=""),"",IF(TODAY()<EDATE(F17,G17),0,MIN(D17,ROUND(D17*DATEDIF(F17,TODAY(),"m")/H17,0))))
G18: 12 | H18: 48 | I18: =IF(OR(D18="",F18=""),"",IF(TODAY()<EDATE(F18,G18),0,MIN(D18,ROUND(D18*DATEDIF(F18,TODAY(),"m")/H18,0))))
G19: 12 | H19: 48 | I19: =IF(OR(D19="",F19=""),"",IF(TODAY()<EDATE(F19,G19),0,MIN(D19,ROUND(D19*DATEDIF(F19,TODAY(),"m")/H19,0))))
G20: 12 | H20: 48 | I20: =IF(OR(D20="",F20=""),"",IF(TODAY()<EDATE(F20,G20),0,MIN(D20,ROUND(D20*DATEDIF(F20,TODAY(),"m")/H20,0))))
G21: 12 | H21: 48 | I21: =IF(OR(D21="",F21=""),"",IF(TODAY()<EDATE(F21,G21),0,MIN(D21,ROUND(D21*DATEDIF(F21,TODAY(),"m")/H21,0))))
G22: 12 | H22: 48 | I22: =IF(OR(D22="",F22=""),"",IF(TODAY()<EDATE(F22,G22),0,MIN(D22,ROUND(D22*DATEDIF(F22,TODAY(),"m")/H22,0))))
G23: 12 | H23: 48 | I23: =IF(OR(D23="",F23=""),"",IF(TODAY()<EDATE(F23,G23),0,MIN(D23,ROUND(D23*DATEDIF(F23,TODAY(),"m")/H23,0))))
G24: 12 | H24: 48 | I24: =IF(OR(D24="",F24=""),"",IF(TODAY()<EDATE(F24,G24),0,MIN(D24,ROUND(D24*DATEDIF(F24,TODAY(),"m")/H24,0))))
G25: 12 | H25: 48 | I25: =IF(OR(D25="",F25=""),"",IF(TODAY()<EDATE(F25,G25),0,MIN(D25,ROUND(D25*DATEDIF(F25,TODAY(),"m")/H25,0))))
G26: 12 | H26: 48 | I26: =IF(OR(D26="",F26=""),"",IF(TODAY()<EDATE(F26,G26),0,MIN(D26,ROUND(D26*DATEDIF(F26,TODAY(),"m")/H26,0))))
... G30: 12 | H30: 48 | I30: =IF(OR(D30="",F30=""),"",IF(TODAY()<EDATE(F30,G30),0,MIN(D30,ROUND(D30*DATEDIF(F30,TODAY(),"m")/H30,0))))
A32: C. Grant guideline by level — set once, deviate only with a written reason
A33: Level | B33: Role examples | C33: % of fully diluted | D33: Options (at current pool) | E33: Cash band ref | I33: Note
A34: L6 — Function head / first exec | B34: Head of Sales, CTO | C34: 0.015 | D34: =ROUND(C34*$B$7/$B$6,0) | E34: see Comp Bands | I34: Cap the first exec grant; you will need room for their successor.
A35: L5 — Senior individual contributor / lead | B35: Lead engineer, senior CSM | C35: 0.006 | D35: =ROUND(C35*$B$7/$B$6,0) | E35: see Comp Bands
A36: L4 — Mid | B36: Engineer, implementation lead | C36: 0.003 | D36: =ROUND(C36*$B$7/$B$6,0) | E36: see Comp Bands
A37: L3 — Junior | B37: Support, junior engineer | C37: 0.001 | D37: =ROUND(C37*$B$7/$B$6,0) | E37: see Comp Bands | I37: Small but real. A grant of zero says something.
A38: Advisor | B38: Fuel-industry veteran, SaaS operator | C38: 0.0025 | D38: =ROUND(C38*$B$7/$B$6,0) | E38: see Comp Bands | I38: 0.1–0.5% over 2 years with a quarterly vest is the usual shape. VERIFY LIVE.
A40: Liquidity warning: in a bootstrapped company that may never exit, an ESOP is a promise with no market. Say so out loud when you grant it, and consider a written buy-back commitment or a phantom/SAR structure instead — lesson 10 §8.

Sheet CEO Dashboard
A1: CEO Dashboard — the monthly instrument panel
A2: Fills C29's companion. Deliberately NOT the COO's weekly KPI Scorecard: fewer rows, a monthly beat, and cash and strategy at the top. Fill one column per month by the 5th. Status computes from Direction, Goal and Red line.
H3: Month → | I3: 46266 | J3: =EDATE(I3,1) | K3: =EDATE(J3,1) | L3: =EDATE(K3,1) | M3: =EDATE(L3,1) | N3: =EDATE(M3,1) | O3: =EDATE(N3,1) | P3: =EDATE(O3,1) | Q3: =EDATE(P3,1) | ... T3: =EDATE(S3,1)
A4: # | B4: Metric | C4: Owner | D4: Source | E4: Unit | F4: Direction | G4: Goal (Green) | H4: Red line | U4: Last | V4: Status
A5: CASH AND SURVIVAL
A6: 1 | B6: Cash in bank (₹, month end) | C6: CEO | D6: Bank statement, personally checked | E6: ₹ | F6: Higher is better | G6: 2000000 | H6: 800000 | U6: =IFERROR(LOOKUP(2,1/(I6:T6<>""),I6:T6),"") | V6: =IF(U6="","",IF(F6="Higher is better",IF(U6>=G6,"GREEN",IF(U6<=H6,"RED","AMBER")),IF(U6<=G6,"GREEN",IF(U6>=H6,"RED","AMBER"))))
A7: 2 | B7: Net burn (₹/month) | C7: CEO with CA | D7: Runway & Scenarios | E7: ₹ | F7: Lower is better | G7: 150000 | H7: 250000 | U7: =IFERROR(LOOKUP(2,1/(I7:T7<>""),I7:T7),"") | V7: =IF(U7="","",IF(F7="Higher is better",IF(U7>=G7,"GREEN",IF(U7<=H7,"RED","AMBER")),IF(U7<=G7,"GREEN",IF(U7>=H7,"RED","AMBER"))))
A8: 3 | B8: Runway (months, net of exit reserve) | C8: CEO | D8: Runway & Scenarios col I | E8: months | F8: Higher is better | G8: 12 | H8: 6 | U8: =IFERROR(LOOKUP(2,1/(I8:T8<>""),I8:T8),"") | V8: =IF(U8="","",IF(F8="Higher is better",IF(U8>=G8,"GREEN",IF(U8<=H8,"RED","AMBER")),IF(U8<=G8,"GREEN",IF(U8>=H8,"RED","AMBER"))))
A9: 4 | B9: Exit reserve still intact (₹) | C9: CEO | D9: Runway & Scenarios, ring-fenced line | E9: ₹ | F9: Higher is better | G9: 450000 | H9: 450000 | U9: =IFERROR(LOOKUP(2,1/(I9:T9<>""),I9:T9),"") | V9: =IF(U9="","",IF(F9="Higher is better",IF(U9>=G9,"GREEN",IF(U9<=H9,"RED","AMBER")),IF(U9<=G9,"GREEN",IF(U9>=H9,"RED","AMBER"))))
A10: REVENUE AND CUSTOMERS
A11: 6 | B11: Paying GSTINs | C11: CEO | D11: Billing system | E11: count | F11: Higher is better | G11: 20 | H11: 8 | U11: =IFERROR(LOOKUP(2,1/(I11:T11<>""),I11:T11),"") | V11: =IF(U11="","",IF(F11="Higher is better",IF(U11>=G11,"GREEN",IF(U11<=H11,"RED","AMBER")),IF(U11<=G11,"GREEN",IF(U11>=H11,"RED","AMBER"))))
A12: 7 | B12: MRR (₹) | C12: CEO | D12: Billing system = paying GSTINs × C11 price | E12: ₹ | F12: Higher is better | G12: 36000 | H12: 14400 | U12: =IFERROR(LOOKUP(2,1/(I12:T12<>""),I12:T12),"") | V12: =IF(U12="","",IF(F12="Higher is better",IF(U12>=G12,"GREEN",IF(U12<=H12,"RED","AMBER")),IF(U12<=G12,"GREEN",IF(U12>=H12,"RED","AMBER"))))
A13: 8 | B13: Net new paying firms this month | C13: CEO | D13: Billing system | E13: count | F13: Higher is better | G13: 2 | H13: 0 | U13: =IFERROR(LOOKUP(2,1/(I13:T13<>""),I13:T13),"") | V13: =IF(U13="","",IF(F13="Higher is better",IF(U13>=G13,"GREEN",IF(U13<=H13,"RED","AMBER")),IF(U13<=G13,"GREEN",IF(U13>=H13,"RED","AMBER"))))
A14: 9 | B14: Logo churn this month | C14: CEO | D14: Billing system | E14: % | F14: Lower is better | G14: 0.01 | H14: 0.03 | U14: =IFERROR(LOOKUP(2,1/(I14:T14<>""),I14:T14),"") | V14: =IF(U14="","",IF(F14="Higher is better",IF(U14>=G14,"GREEN",IF(U14<=H14,"RED","AMBER")),IF(U14<=G14,"GREEN",IF(U14>=H14,"RED","AMBER"))))
A15: 10 | B15: Districts with ≥1 paying dealer | C15: CEO | D15: CRM | E15: count | F15: Higher is better | G15: 3 | H15: 1 | U15: =IFERROR(LOOKUP(2,1/(I15:T15<>""),I15:T15),"") | V15: =IF(U15="","",IF(F15="Higher is better",IF(U15>=G15,"GREEN",IF(U15<=H15,"RED","AMBER")),IF(U15<=G15,"GREEN",IF(U15>=H15,"RED","AMBER"))))
A16: STRATEGY AND MARKET
A17: 12 | B17: Strategy-bet progress (0–100%) | C17: CEO | D17: Annual Plan & OKRs | E17: % | F17: Higher is better | G17: 0.75 | H17: 0.4 | U17: =IFERROR(LOOKUP(2,1/(I17:T17<>""),I17:T17),"") | V17: =IF(U17="","",IF(F17="Higher is better",IF(U17>=G17,"GREEN",IF(U17<=H17,"RED","AMBER")),IF(U17<=G17,"GREEN",IF(U17>=H17,"RED","AMBER"))))
A18: 13 | B18: Assumptions tested this quarter | C18: CEO | D18: Strategy Kernel tab C | E18: count | F18: Higher is better | G18: 2 | H18: 0 | U18: =IFERROR(LOOKUP(2,1/(I18:T18<>""),I18:T18),"") | V18: =IF(U18="","",IF(F18="Higher is better",IF(U18>=G18,"GREEN",IF(U18<=H18,"RED","AMBER")),IF(U18<=G18,"GREEN",IF(U18>=H18,"RED","AMBER"))))
A19: 14 | B19: Founder customer conversations this month | C19: CEO | D19: Pipeline tab | E19: count | F19: Higher is better | G19: 20 | H19: 8 | U19: =IFERROR(LOOKUP(2,1/(I19:T19<>""),I19:T19),"") | V19: =IF(U19="","",IF(F19="Higher is better",IF(U19>=G19,"GREEN",IF(U19<=H19,"RED","AMBER")),IF(U19<=G19,"GREEN",IF(U19>=H19,"RED","AMBER"))))
A20: 15 | B20: Weighted pipeline (₹ ARR) | C20: CEO | D20: Pipeline tab | E20: ₹ | F20: Higher is better | G20: 300000 | H20: 100000 | U20: =IFERROR(LOOKUP(2,1/(I20:T20<>""),I20:T20),"") | V20: =IF(U20="","",IF(F20="Higher is better",IF(U20>=G20,"GREEN",IF(U20<=H20,"RED","AMBER")),IF(U20<=G20,"GREEN",IF(U20>=H20,"RED","AMBER"))))
A21: PEOPLE
A22: 17 | B22: Open roles past 60 days | C22: CEO | D22: Hiring tracker | E22: count | F22: Lower is better | G22: 0 | H22: 2 | U22: =IFERROR(LOOKUP(2,1/(I22:T22<>""),I22:T22),"") | V22: =IF(U22="","",IF(F22="Higher is better",IF(U22>=G22,"GREEN",IF(U22<=H22,"RED","AMBER")),IF(U22<=G22,"GREEN",IF(U22>=H22,"RED","AMBER"))))
A23: 18 | B23: Regretted attrition (rolling 12m) | C23: CEO | D23: HR record | E23: count | F23: Lower is better | G23: 0 | H23: 1 | U23: =IFERROR(LOOKUP(2,1/(I23:T23<>""),I23:T23),"") | V23: =IF(U23="","",IF(F23="Higher is better",IF(U23>=G23,"GREEN",IF(U23<=H23,"RED","AMBER")),IF(U23<=G23,"GREEN",IF(U23>=H23,"RED","AMBER"))))
A24: 19 | B24: Team size (FTE + contractors) | C24: COO | D24: Headcount plan | E24: count | F24: Higher is better | G24: 5 | H24: 3 | U24: =IFERROR(LOOKUP(2,1/(I24:T24<>""),I24:T24),"") | V24: =IF(U24="","",IF(F24="Higher is better",IF(U24>=G24,"GREEN",IF(U24<=H24,"RED","AMBER")),IF(U24<=G24,"GREEN",IF(U24>=H24,"RED","AMBER"))))
A25: GOVERNANCE AND TRUST
A26: 21 | B26: Statutory / board misses this month | C26: CEO with CS | D26: Board Calendar | E26: count | F26: Lower is better | G26: 0 | H26: 1 | U26: =IFERROR(LOOKUP(2,1/(I26:T26<>""),I26:T26),"") | V26: =IF(U26="","",IF(F26="Higher is better",IF(U26>=G26,"GREEN",IF(U26<=H26,"RED","AMBER")),IF(U26<=G26,"GREEN",IF(U26>=H26,"RED","AMBER"))))
A27: 22 | B27: Money-affecting product incidents | C27: CEO | D27: Incident log (COO T17) | E27: count | F27: Lower is better | G27: 0 | H27: 1 | U27: =IFERROR(LOOKUP(2,1/(I27:T27<>""),I27:T27),"") | V27: =IF(U27="","",IF(F27="Higher is better",IF(U27>=G27,"GREEN",IF(U27<=H27,"RED","AMBER")),IF(U27<=G27,"GREEN",IF(U27>=H27,"RED","AMBER"))))
A28: 23 | B28: Days since the CEO last spoke to a paying dealer | C28: CEO | D28: Calendar | E28: days | F28: Lower is better | G28: 7 | H28: 21 | U28: =IFERROR(LOOKUP(2,1/(I28:T28<>""),I28:T28),"") | V28: =IF(U28="","",IF(F28="Higher is better",IF(U28>=G28,"GREEN",IF(U28<=H28,"RED","AMBER")),IF(U28<=G28,"GREEN",IF(U28>=H28,"RED","AMBER"))))
B30: Rule: a metric that is RED two months running becomes an agenda item at the next board meeting automatically, without a vote. A metric that has not driven a decision in two quarters gets deleted.

Sheet Annual Plan & OKRs
A1: Annual Plan & OKRs — the year's bet, the objectives, and the honest confidence
A2: Fills C28. Set annually, scored quarterly. Three to five objectives, never more. Confidence is typed by the owner, not computed — a falling confidence line is the earliest warning the plan has of anything.
A4: A. The year
A5: Year | B5: FY 2026-27
A6: The one thing that must be true by year end | B6: Twenty paying GSTINs across three Chhattisgarh districts, renewing, with a written and tested sales script.
A7: The bet we are making | B7: That district-level proof and dealer-to-dealer referral beats broad marketing for this buyer.
A8: What we are deliberately not doing this year | B8: No pan-India push, no second product, no OMC pursuit beyond one founder-quarter, no outside capital unless the trigger in C13 fires.
A10: B. Objectives and key results
A11: # | B11: Objective / Key result | C11: Owner | D11: Baseline | E11: Target | F11: Current | G11: % done | H11: Confidence | I11: Quarter | J11: Note / what would make this red
A12: O1 — Prove the district motion | I12: Q1–Q4
A13: KR | B13: Paying GSTINs | C13: CEO | D13: 0 | E13: 20 | F13: 0 | G13: =IF(OR(D13="",E13="",E13=D13),"",(F13-D13)/(E13-D13)) | H13: 0.6 | I13: Q4 | J13: Counted as billed and collected, not as signed.
A14: KR | B14: Districts with ≥1 paying dealer | C14: CEO | D14: 0 | E14: 3 | F14: 0 | G14: =IF(OR(D14="",E14="",E14=D14),"",(F14-D14)/(E14-D14)) | H14: 0.5 | I14: Q4
A15: KR | B15: Written sales script tested on ≥20 conversations | C15: CEO | D15: 0 | E15: 20 | F15: 0 | G15: =IF(OR(D15="",E15="",E15=D15),"",(F15-D15)/(E15-D15)) | H15: 0.7 | I15: Q2
A16: O2 — Make onboarding survive without a founder | I16: Q2–Q4
A17: KR | B17: Median days from signup to first invoice | C17: COO | D17: 21 | E17: 7 | F17: 21 | G17: =IF(OR(D17="",E17="",E17=D17),"",(F17-D17)/(E17-D17)) | H17: 0.5 | I17: Q3 | J17: Lower is better — invert the % done formula for this row.
A18: KR | B18: Dealers onboarded with no founder on site | C18: COO | D18: 0 | E18: 3 | F18: 0 | G18: =IF(OR(D18="",E18="",E18=D18),"",(F18-D18)/(E18-D18)) | H18: 0.4 | I18: Q4
A19: O3 — Stay default alive | I19: Q1–Q4
A20: KR | B20: Runway at year end (months) | C20: CEO | D20: 14 | E20: 12 | F20: 14 | G20: =IF(OR(D20="",E20="",E20=D20),"",(F20-D20)/(E20-D20)) | H20: 0.6 | I20: Q4 | J20: Below 9 at any point triggers the C13 ladder.
A21: KR | B21: Gross margin % | C21: CEO | D21: 0.55 | E21: 0.7 | F21: 0.55 | G21: =IF(OR(D21="",E21="",E21=D21),"",(F21-D21)/(E21-D21)) | H21: 0.45 | I21: Q4 | J21: SMS and support cost are the two levers.
A22: O4 — Earn the right to be trusted with a dealer's money | I22: Q1–Q4
A23: KR | B23: Money-affecting incidents | C23: CEO | D23: 1 | E23: 0 | F23: 0 | G23: =IF(OR(D23="",E23="",E23=D23),"",(F23-D23)/(E23-D23)) | H23: 0.6 | I23: Q4 | J23: One is too many. This row never gets deleted.
A24: KR | B24: Board meetings held on schedule with signed minutes | C24: CEO | D24: 0 | E24: 4 | F24: 0 | G24: =IF(OR(D24="",E24="",E24=D24),"",(F24-D24)/(E24-D24)) | H24: 0.8 | I24: Q4
A26: C. Quarterly review — what actually happened
A27: Q | B27: What we said we'd do | C27: What happened | D27: Score 0–1 | E27: Persist / adjust / kill | F27: Decision Journal ID | J27: Lesson learned
A28: Q1
A29: Q2
A30: Q3
A31: Q4

Sheet Decision Journal
A1: Decision Journal — the record that turns experience into calibration
A2: Fills C29. Write the entry BEFORE the outcome is known; that is the entire point. Review open rows every quarter. The Verdict column exists to stop you rewarding luck: a good decision with a bad outcome is still a good decision.
A4: ID | B4: Date | C4: The decision | D4: Door | E4: Clock | F4: Options considered (incl. do nothing) | G4: Chosen because | H4: What would change my mind | I4: Confidence | J4: Review on | K4: What actually happened | L4: Outcome | M4: Verdict (computed)
A5: DJ-001 | B5: 46232 | C5: Charge per GSTIN, not per user; bill on the web only, not in-app. | D5: One-way | E5: Year | F5: (a) per user (b) per transaction (c) % of volume (d) per GSTIN (e) free + services. Do nothing = stay free. | G5: GSTIN is the unit the dealer already thinks in and already pays tax against; it scales with his business without punishing him for adding staff. Web-only billing keeps 15–30% of revenue that would otherwise go to app-store commission. | H5: If >30% of qualified dealers refuse to complete a web payment, or if multi-GSTIN dealers turn out to be <10% of the base. | I5: 0.75 | J5: 46418 | M5: =IF(OR(L5="",I5=""),"open",IF(AND(I5>=0.6,L5="Good"),"Good decision, good outcome",IF(AND(I5>=0.6,L5="Bad"),"Good decision, bad outcome — do not change the process",IF(L5="Good","Bad decision, good outcome — do not repeat it","Bad decision, bad outcome — change the process"))))
M6: =IF(C6="","",IF(OR(L6="",I6=""),"open",IF(AND(I6>=0.6,L6="Good"),"Good decision, good outcome",IF(AND(I6>=0.6,L6="Bad"),"Good decision, bad outcome — do not change the process",IF(L6="Good","Bad decision, good outcome — do not repeat it","Bad decision, bad outcome — change the process")))))
M7: =IF(C7="","",IF(OR(L7="",I7=""),"open",IF(AND(I7>=0.6,L7="Good"),"Good decision, good outcome",IF(AND(I7>=0.6,L7="Bad"),"Good decision, bad outcome — do not change the process",IF(L7="Good","Bad decision, good outcome — do not repeat it","Bad decision, bad outcome — change the process")))))
M8: =IF(C8="","",IF(OR(L8="",I8=""),"open",IF(AND(I8>=0.6,L8="Good"),"Good decision, good outcome",IF(AND(I8>=0.6,L8="Bad"),"Good decision, bad outcome — do not change the process",IF(L8="Good","Bad decision, good outcome — do not repeat it","Bad decision, bad outcome — change the process")))))
M9: =IF(C9="","",IF(OR(L9="",I9=""),"open",IF(AND(I9>=0.6,L9="Good"),"Good decision, good outcome",IF(AND(I9>=0.6,L9="Bad"),"Good decision, bad outcome — do not change the process",IF(L9="Good","Bad decision, good outcome — do not repeat it","Bad decision, bad outcome — change the process")))))
M10: =IF(C10="","",IF(OR(L10="",I10=""),"open",IF(AND(I10>=0.6,L10="Good"),"Good decision, good outcome",IF(AND(I10>=0.6,L10="Bad"),"Good decision, bad outcome — do not change the process",IF(L10="Good","Bad decision, good outcome — do not repeat it","Bad decision, bad outcome — change the process")))))
M11: =IF(C11="","",IF(OR(L11="",I11=""),"open",IF(AND(I11>=0.6,L11="Good"),"Good decision, good outcome",IF(AND(I11>=0.6,L11="Bad"),"Good decision, bad outcome — do not change the process",IF(L11="Good","Bad decision, good outcome — do not repeat it","Bad decision, bad outcome — change the process")))))
M12: =IF(C12="","",IF(OR(L12="",I12=""),"open",IF(AND(I12>=0.6,L12="Good"),"Good decision, good outcome",IF(AND(I12>=0.6,L12="Bad"),"Good decision, bad outcome — do not change the process",IF(L12="Good","Bad decision, good outcome — do not repeat it","Bad decision, bad outcome — change the process")))))
M13: =IF(C13="","",IF(OR(L13="",I13=""),"open",IF(AND(I13>=0.6,L13="Good"),"Good decision, good outcome",IF(AND(I13>=0.6,L13="Bad"),"Good decision, bad outcome — do not change the process",IF(L13="Good","Bad decision, good outcome — do not repeat it","Bad decision, bad outcome — change the process")))))
M14: =IF(C14="","",IF(OR(L14="",I14=""),"open",IF(AND(I14>=0.6,L14="Good"),"Good decision, good outcome",IF(AND(I14>=0.6,L14="Bad"),"Good decision, bad outcome — do not change the process",IF(L14="Good","Bad decision, good outcome — do not repeat it","Bad decision, bad outcome — change the process")))))
M15: =IF(C15="","",IF(OR(L15="",I15=""),"open",IF(AND(I15>=0.6,L15="Good"),"Good decision, good outcome",IF(AND(I15>=0.6,L15="Bad"),"Good decision, bad outcome — do not change the process",IF(L15="Good","Bad decision, good outcome — do not repeat it","Bad decision, bad outcome — change the process")))))
M16: =IF(C16="","",IF(OR(L16="",I16=""),"open",IF(AND(I16>=0.6,L16="Good"),"Good decision, good outcome",IF(AND(I16>=0.6,L16="Bad"),"Good decision, bad outcome — do not change the process",IF(L16="Good","Bad decision, good outcome — do not repeat it","Bad decision, bad outcome — change the process")))))
M17: =IF(C17="","",IF(OR(L17="",I17=""),"open",IF(AND(I17>=0.6,L17="Good"),"Good decision, good outcome",IF(AND(I17>=0.6,L17="Bad"),"Good decision, bad outcome — do not change the process",IF(L17="Good","Bad decision, good outcome — do not repeat it","Bad decision, bad outcome — change the process")))))
... M45: =IF(C45="","",IF(OR(L45="",I45=""),"open",IF(AND(I45>=0.6,L45="Good"),"Good decision, good outcome",IF(AND(I45>=0.6,L45="Bad"),"Good decision, bad outcome — do not change the process",IF(L45="Good","Bad decision, good outcome — do not repeat it","Bad decision, bad outcome — change the process")))))
C47: Door: One-way (hard to reverse — slow down, gather more) or Two-way (cheap to reverse — decide fast and move). Clock: Week / Year / Decade. Outcome: type Good or Bad at the review date.

Sheet Board Calendar
A1: Board Calendar — meetings, the statutory gap, and what the CEO personally signs
A2: Fills C17 and C18. Every section number, form and due date below is VERIFY LIVE — confirm with the Company Secretary before relying on it. The COO's Compliance Calendar owns the filing machinery; this sheet owns the board's own trail.
A4: A. Board meetings — Companies Act 2013 §173 (VERIFY LIVE with the CS)
A5: # | B5: Date | C5: Type | D5: Gap from previous (days) | E5: Notice sent | F5: Pack circulated | G5: Quorum met | H5: Minutes signed on | I5: Key resolutions / decisions taken
A6: 1 | B6: 46162 | C6: Q1 board
A7: 2 | B7: 46253 | C7: Q2 board | D7: =B7-B6
A8: 3 | B8: 46344 | C8: Q3 board | D8: =B8-B7
A9: 4 | B9: 46435 | C9: Q4 board + accounts | D9: =B9-B8
D10: =IF(OR(B10="",B9=""),"",B10-B9)
D11: =IF(OR(B11="",B10=""),"",B11-B10)
D12: =IF(OR(B12="",B11=""),"",B12-B11)
D13: =IF(OR(B13="",B12=""),"",B13-B12)
I14: Red gap = more than 120 days between meetings. Confirm the exact statutory limit and any small-company relaxation with the CS — VERIFY LIVE.
A15: B. The annual trail the CEO personally signs or tables
A16: # | B16: Item | C16: Form (VERIFY LIVE) | D16: Statutory due (VERIFY LIVE) | E16: Our target date | F16: Owner | G16: Status | H16: Evidence / file | I16: Note
A17: 1 | B17: Disclosure of interest by every director | C17: MBP-1 | D17: First board meeting of the FY, and on any change | F17: CS | G17: Not started | I17: Critical in a family company — relatives' firms count as related parties.
A18: 2 | B18: Declaration of non-disqualification | C18: DIR-8 | D18: First board meeting of the FY | F18: CS | G18: Not started
A19: 3 | B19: Register of contracts in which directors are interested | C19: MBP-4 / register | D19: Maintained continuously | F19: CS | G19: Not started | I19: Any transaction with a relative's firm goes here before it happens, not after.
A20: 4 | B20: Board's report and financial statements approved | C20: Board resolution | D20: Before the AGM | F20: CEO + CA | G20: Not started | I20: The CEO signs. Read them first — signing without reading is the failure.
A21: 5 | B21: Annual General Meeting | C21: — | D21: Within the statutory window after FY end | F21: CS | G21: Not started
A22: 6 | B22: Financial statements filed | C22: AOC-4 | D22: After the AGM | F22: CS + CA | G22: Not started
A23: 7 | B23: Annual return filed | C23: MGT-7 / MGT-7A | D23: After the AGM | F23: CS | G23: Not started | I23: Small companies may use the abridged form — confirm eligibility.
A24: 8 | B24: Director KYC | C24: DIR-3 KYC | D24: Annual, per director | F24: Each director personally | G24: Not started | I24: Missing this deactivates the DIN. It is the cheapest way to embarrass yourself.
A25: 9 | B25: Return of deposits | C25: DPT-3 | D25: Annual | F25: CS + CA | G25: Not started | I25: Catches director loans — relevant if founders fund the company.
A26: 10 | B26: MSME payment return | C26: MSME-1 | D26: Half-yearly | F26: CS + CA | G26: Not started | I26: Applies to dues outstanding to MSME suppliers.
A27: 11 | B27: Auditor appointment / ratification | C27: ADT-1 | D27: On appointment | F27: CS | G27: Not started
A28: 12 | B28: Statutory registers up to date | C28: Registers | D28: Continuous | F28: CS | G28: Not started | I28: A future investor's diligence starts here.
A30: C. Advisory board — the outside voice a family board most needs
A31: # | B31: Name | C31: Why them | D31: Ask | E31: Offer | F31: Cadence | G31: Approached on | H31: Status | I31: Standing agenda slot
A32: 1 | B32: Fuel-industry veteran (ex-OMC or large dealer) | C32: Knows the buyer better than we do | D32: 2 hours/month + intros | E32: 0.1–0.25% over 2 years, quarterly vest — VERIFY structure with CS | F32: Monthly call | H32: Not approached | I32: Yes
A33: 2 | B33: Indian B2B SaaS operator | C33: Has sold to SMBs at this ticket size | D33: Quarterly review of the strategy kernel | E33: 0.1–0.25% over 2 years | F33: Quarterly | H33: Not approached | I33: Yes
A34: 3 | B34: Independent finance person (not our CA) | C34: Reads the numbers with no stake in the story | D34: Attend two board meetings a year | E34: Honorarium | F34: Half-yearly | H34: Not approached | I34: Yes

Sheet Pipeline
A1: Pipeline — the CEO's own founder-led sales pipeline
A2: Fills C10. This is the CEO's personal list, not the CRM — the COO course owns CRM hygiene and stage definitions. The only two columns that matter are Next step and Next date; a blank pair means the deal is dead and you have not admitted it.
A4: Dealer / firm | B4: District | C4: GSTINs | D4: Contact + role | E4: Source | F4: Stage | G4: Stage since | H4: Next step (a verb and a name) | I4: Next date | J4: ₹ ARR potential | K4: Prob. | L4: Weighted ₹ | M4: The objection actually blocking this | N4: Loss reason (if lost)
A5: Example Fuels, Raipur | B5: Raipur | C5: 2 | D5: Owner, 52 | E5: Dealer association meet | F5: 3 Demo done | G5: 46252 | H5: Call owner's accountant with the Tally export sample — CEO | I5: 46262 | J5: 60000 | K5: 0.3 | L5: =IF(OR(J5="",K5=""),"",J5*K5) | M5: "My accountant already does this in Tally"
L6: =IF(OR(J6="",K6=""),"",J6*K6)
L7: =IF(OR(J7="",K7=""),"",J7*K7)
L8: =IF(OR(J8="",K8=""),"",J8*K8)
L9: =IF(OR(J9="",K9=""),"",J9*K9)
L10: =IF(OR(J10="",K10=""),"",J10*K10)
L11: =IF(OR(J11="",K11=""),"",J11*K11)
L12: =IF(OR(J12="",K12=""),"",J12*K12)
L13: =IF(OR(J13="",K13=""),"",J13*K13)
L14: =IF(OR(J14="",K14=""),"",J14*K14)
L15: =IF(OR(J15="",K15=""),"",J15*K15)
L16: =IF(OR(J16="",K16=""),"",J16*K16)
L17: =IF(OR(J17="",K17=""),"",J17*K17)
... L45: =IF(OR(J45="",K45=""),"",J45*K45)
A47: Summary
A48: Open deals | B48: =COUNTIFS(F5:F45,"<>",F5:F45,"<>X Lost") | D48: Weighted pipeline ₹ | E48: =SUMIFS(L5:L45,F5:F45,"<>X Lost") | G48: Overdue next steps | H48: =COUNTIFS(I5:I45,"<"&TODAY(),F5:F45,"<>X Lost")
A50: Objection bank — every objection heard, and the answer that worked
A51: Objection (in the dealer's words) | B51: Times heard | C51: What is really being said | D51: The answer that worked | E51: Proof to show
A52: "My accountant already does this in Tally" | B52: 8 | C52: I don't want a second system, and my accountant is my trusted adviser | D52: We don't replace Tally, we feed it. Your accountant gets a cleaner export and stops chasing you for missing slips. | E52: A Tally-ready export from a real dealer's month
A53: "My customers will never use an app" | B53: 7 | C53: I'll end up doing double work | D53: The dealer-side works alone. Customer confirmations are a bonus, and we onboard your top 5 customers ourselves. | E53: Confirmation rate from an existing dealer's customers
A54: "What if you shut down? My data is in there." | B54: 6 | C54: You're three people in Raipur | D54: One-click full export any day, in your name, and a written data-return clause in the contract. | E54: The export, run live on his phone
A55: "It's too costly" | B55: 9 | C55: I can't see the return yet | D55: Show his own reconciliation hours and last quarter's credit leakage. Price against that, not against ₹0. | E55: His own numbers, on paper
A56: "Send me details on WhatsApp, I'll see" | B56: 12 | C56: Polite no | D56: Ask for a 20-minute slot at his pump at his quietest hour, with his accountant present. | E56: A calendar invite, before you leave the room

Sheet Comp Bands
A1: Comp Bands — salary and equity by role and level, plus the offer check
A2: Fills C20. Bands are illustrative and MUST be re-benchmarked before any offer — VERIFY LIVE. Publishing a band internally is a culture decision, not a payroll one; decide it deliberately (lesson 11).
A4: A. Bands (annual CTC ₹, Raipur / remote-India)
A5: Role family | B5: Level | C5: Min ₹ | D5: Mid ₹ | E5: Max ₹ | F5: Equity % | G5: Options | H5: Location factor | I5: Note
A6: Engineering | B6: L3 | C6: 400000 | D6: 550000 | E6: 700000 | F6: 0.001 | G6: =ROUND(F6*'ESOP Pool'!$B$7/'ESOP Pool'!$B$6,0) | H6: 1 | I6: Junior / 0–2 yrs
A7: Engineering | B7: L4 | C7: 700000 | D7: 950000 | E7: 1200000 | F7: 0.003 | G7: =ROUND(F7*'ESOP Pool'!$B$7/'ESOP Pool'!$B$6,0) | H7: 1 | I7: Mid / 2–5 yrs
A8: Engineering | B8: L5 | C8: 1200000 | D8: 1600000 | E8: 2100000 | F8: 0.006 | G8: =ROUND(F8*'ESOP Pool'!$B$7/'ESOP Pool'!$B$6,0) | H8: 1 | I8: Senior / lead
A9: Engineering | B9: L6 | C9: 2000000 | D9: 2600000 | E9: 3400000 | F9: 0.015 | G9: =ROUND(F9*'ESOP Pool'!$B$7/'ESOP Pool'!$B$6,0) | H9: 1 | I9: CTO / function head — expect to pay above band or pay in equity
A10: Implementation / Support | B10: L3 | C10: 250000 | D10: 340000 | E10: 430000 | F10: 0.001 | G10: =ROUND(F10*'ESOP Pool'!$B$7/'ESOP Pool'!$B$6,0) | H10: 1 | I10: Field-capable; this is the role that decides whether onboarding scales
A11: Implementation / Support | B11: L4 | C11: 430000 | D11: 560000 | E11: 700000 | F11: 0.002 | G11: =ROUND(F11*'ESOP Pool'!$B$7/'ESOP Pool'!$B$6,0) | H11: 1
A12: Sales | B12: L4 | C12: 400000 | D12: 550000 | E12: 700000 | F12: 0.002 | G12: =ROUND(F12*'ESOP Pool'!$B$7/'ESOP Pool'!$B$6,0) | H12: 1 | I12: Plus variable — set the variable at 30–40% of target CTC
A13: Sales | B13: L6 | C13: 1200000 | D13: 1600000 | E13: 2200000 | F13: 0.012 | G13: =ROUND(F13*'ESOP Pool'!$B$7/'ESOP Pool'!$B$6,0) | H13: 1 | I13: First sales leader; do not hire before the script exists
A14: Founder-Director | B14: — | C14: 600000 | D14: 900000 | E14: 1200000 | F14: 0 | G14: =ROUND(F14*'ESOP Pool'!$B$7/'ESOP Pool'!$B$6,0) | H14: 1 | I14: Directors' remuneration for a Pvt Ltd needs a board resolution — confirm with the CS. Pay yourself something.
A16: B. Offer check — fill before the offer goes out
A17: Field | B17: Value | I17: Check
A18: Candidate | B18: A. Example
A19: Role family | B19: Engineering
A20: Level | B20: L4
A21: Proposed CTC (₹) | B21: 1000000
A22: Proposed options | B22: 300
A23: Band mid for this level (₹) | B23: =SUMPRODUCT((A6:A14=B19)*(B6:B14=B20)*D6:D14)
A24: Inside band? | B24: =IF(B23="","",IF(AND(B21>=B23*0.75,B21<=B23*1.3),"Yes","OUTSIDE BAND — write the reason below and get a second opinion")) | I24: An outside-band offer is allowed. An undocumented one is not.
A25: Reason if outside band
A26: Would we pay this to an existing person doing the same job?
A28: Family-fairness rule (lesson 11): a related employee is paid from the same band, evaluated against criteria written before the review, and gets more scrutiny than anyone else — not less. Write the deviation down or do not make it.

Sheet Risk & Pre-Mortem
A1: Risk & Pre-Mortem — it is 24 months from now and VSYST failed. Why?
A2: Fills C30. The COO workbook's Risk Register owns operational risk; this sheet owns the existential kind. Run the pre-mortem with all three founders in the room, silently and in writing first, then compare — that is what stops the loudest voice setting the list.
A4: A. Pre-mortem — causes of death, scored
A5: # | B5: Cause of failure | C5: Likelihood 1-5 | D5: Impact 1-5 | E5: Score | F5: The early-warning signal we would actually see | G5: Mitigation (a dated action, not an intention) | H5: Owner | I5: By when | J5: Status
A6: 1 | B6: We run out of cash before the district motion is proven | C6: 3 | D6: 5 | E6: =C6*D6 | F6: Runway falls below 9 months on the CEO Dashboard | G6: Trigger ladder in C13 pre-committed; annual prepay pricing; DPIIT/80-IAC and cloud credits applied for this quarter | H6: CEO | I6: 46326 | J6: Open
A7: 2 | B7: Dealers sign up and never reach a first invoice | C7: 4 | D7: 5 | E7: =C7*D7 | F7: Median days-to-first-invoice rising above 14; activation below 50% | G7: Onboarding treated as the product; time-to-first-invoice on the dashboard; onboarding SOP owned by the COO | H7: COO | I7: 46356 | J7: Open
A8: 3 | B8: A ledger or billing bug misstates a dealer's money and destroys trust | C8: 3 | D8: 5 | E8: =C8*D8 | F8: Any money-affecting incident; a reconciliation complaint | G8: Ledger correctness above features; the month-rebuild and check tooling; incident postmortem every time; CEO informed same day | H8: CEO | I8: 46295 | J8: Open
A9: 4 | B9: The founder-CEO stays the only salesperson and the motion never becomes repeatable | C9: 4 | D9: 4 | E9: =C9*D9 | F9: No written script after 20 conversations; CAC not falling; every deal needs the CEO | G9: C10 script and objection bank; first sales hire trigger written down; CEO tracks % of deals not personally closed | H9: CEO | I9: 46387 | J9: Open
A10: 5 | B10: A family disagreement becomes a company disagreement | C10: 3 | D10: 5 | E10: =C10*D10 | F10: A decision reopened twice; a founder silent in a meeting; a conversation that only happens at home | G10: C02 founders' agreement with vesting; C03 decision rights; the disagreement protocol; one outside advisor with a standing slot | H10: CEO | I10: 46310 | J10: Open
A11: 6 | B11: A larger incumbent or an OMC-backed vendor ships an adequate free version | C11: 2 | D11: 5 | E11: =C11*D11 | F11: An OMC circular; a dealer mentioning a bundled tool; an ATG vendor adding billing | G11: Switching-cost moat: ledger, rate history and audit trail; deepen the two-sided customer link; move faster in-district | H11: CEO | I11: 46477 | J11: Open
A12: 7 | B12: A data breach exposes dealer financial data | C12: 2 | D12: 5 | E12: =C12*D12 | F12: Any unauthorised access; a tenant seeing another tenant's data | G12: Tenant isolation audit; DPDP readiness; ISO 27001 roadmap; cyber liability cover priced | H12: CEO + COO | I12: 46477 | J12: Open
A13: 8 | B13: We chase the OMC prize for a year and it converts nothing | C13: 3 | D13: 4 | E13: =C13*D13 | F13: Two quarters of meetings with no written next step or empanelment path | G13: A written kill-criterion and a one-founder-quarter budget; C26 scoring before any further pursuit | H13: CEO | I13: 46356 | J13: Open
A14: 9 | B14: The CEO burns out or a founder becomes unavailable | C14: 3 | D14: 5 | E14: =C14*D14 | F14: Working every Sunday for a month; no holiday in a year; decisions queuing | G14: The COO course's autopilot test; a named backup for every founder-held relationship; a real holiday booked | H14: CEO | I14: 46418 | J14: Open
A15: 10 | B15: We stay pre-revenue because we keep building instead of selling | C15: 4 | D15: 5 | E15: =C15*D15 | F15: Shipping features while the pipeline is empty; more commits than conversations this month | G15: Founder conversations on the CEO Dashboard; the no-list in C25; a weekly minimum of customer conversations | H15: CEO | I15: 46280 | J15: Open
A17: B. Crisis playbooks — written before the crisis, not during
A18: # | B18: Crisis | C18: First hour: who does what | F18: Who speaks, and what the first statement says | G18: Notification obligations (VERIFY LIVE with counsel) | H18: Playbook owner | I18: Last rehearsed | J18: Status
A19: 1 | B19: Dealer financial data breach | C19: CEO informed immediately; access revoked; scope determined before any statement | F19: CEO only. State what is known, what is not, what we are doing, when we will update next. Never speculate on cause. | G19: DPDP Act 2023 obligations to the Data Protection Board and affected persons — confirm timing with counsel | H19: CEO | J19: Not rehearsed
A20: 2 | B20: Ledger error that misstates money | C20: Freeze the affected postings; quantify the blast radius per tenant before contacting anyone | F20: CEO, to each affected dealer personally and by phone first. Exact rupee impact, the correction, and the date it is fixed. | G20: Contractual; possibly GST implications if invoices were affected — confirm with the CA | H20: CEO | J20: Not rehearsed
A21: 3 | B21: Extended outage during the 22:00–06:00 rate-confirmation window | C21: COO runs the incident; CEO handles dealers; fall back to a manual confirmation record | F21: COO for status, CEO for anything that touches a dealer's money or trust | G21: None statutory; contractual SLA if any | H21: COO | J21: Not rehearsed
A22: 4 | B22: Founder or partner dispute becomes public | C22: No response for 24 hours except an acknowledgement; counsel engaged | F22: CEO, one statement, agreed with counsel and co-founders. Never respond in a comment thread. | G22: Depends — take advice before saying anything | H22: CEO | J22: Not rehearsed
A23: 5 | B23: Key person unavailable (illness, accident) | C23: Named backup takes each relationship per the relationship map (lesson 14) | F23: CEO or the designated backup, to team first, then customers | G23: Board informed; check bank/DSC signatory continuity | H23: CEO | J23: Not rehearsed
