Workbook

Sheet Dealer Data
A1: Dealer Name | B1: Oil Company | C1: Trading Area | D1: MS Sale — Petrol (KL) | H1: HSD Sale — Diesel (KL) | L1: Total MS+HSD (KL) Avg / month | M1: Loyalty / Fleet Card monthly avg | O1: UPI monthly avg | Q1: Net Banking Transfers monthly avg
D2: Month 1 | E2: Month 2 | F2: Month 3 | G2: Average | H2: Month 1 | I2: Month 2 | J2: Month 3 | K2: Average | M2: Txn Count | N2: Txn Value (₹) | O2: Txn Count | P2: Txn Value (₹) | Q2: Txn Count | R2: Txn Value (₹) | S2: Avg Ticket (₹)
G3: =IFERROR(AVERAGE(D3:F3),"") | K3: =IFERROR(AVERAGE(H3:J3),"") | L3: =IFERROR(G3+K3,"") | S3: =IFERROR(R3/Q3,"")
G4: =IFERROR(AVERAGE(D4:F4),"") | K4: =IFERROR(AVERAGE(H4:J4),"") | L4: =IFERROR(G4+K4,"") | S4: =IFERROR(R4/Q4,"")
G5: =IFERROR(AVERAGE(D5:F5),"") | K5: =IFERROR(AVERAGE(H5:J5),"") | L5: =IFERROR(G5+K5,"") | S5: =IFERROR(R5/Q5,"")
G6: =IFERROR(AVERAGE(D6:F6),"") | K6: =IFERROR(AVERAGE(H6:J6),"") | L6: =IFERROR(G6+K6,"") | S6: =IFERROR(R6/Q6,"")
G7: =IFERROR(AVERAGE(D7:F7),"") | K7: =IFERROR(AVERAGE(H7:J7),"") | L7: =IFERROR(G7+K7,"") | S7: =IFERROR(R7/Q7,"")
G8: =IFERROR(AVERAGE(D8:F8),"") | K8: =IFERROR(AVERAGE(H8:J8),"") | L8: =IFERROR(G8+K8,"") | S8: =IFERROR(R8/Q8,"")
G9: =IFERROR(AVERAGE(D9:F9),"") | K9: =IFERROR(AVERAGE(H9:J9),"") | L9: =IFERROR(G9+K9,"") | S9: =IFERROR(R9/Q9,"")
G10: =IFERROR(AVERAGE(D10:F10),"") | K10: =IFERROR(AVERAGE(H10:J10),"") | L10: =IFERROR(G10+K10,"") | S10: =IFERROR(R10/Q10,"")
G11: =IFERROR(AVERAGE(D11:F11),"") | K11: =IFERROR(AVERAGE(H11:J11),"") | L11: =IFERROR(G11+K11,"") | S11: =IFERROR(R11/Q11,"")
G12: =IFERROR(AVERAGE(D12:F12),"") | K12: =IFERROR(AVERAGE(H12:J12),"") | L12: =IFERROR(G12+K12,"") | S12: =IFERROR(R12/Q12,"")
G13: =IFERROR(AVERAGE(D13:F13),"") | K13: =IFERROR(AVERAGE(H13:J13),"") | L13: =IFERROR(G13+K13,"") | S13: =IFERROR(R13/Q13,"")
G14: =IFERROR(AVERAGE(D14:F14),"") | K14: =IFERROR(AVERAGE(H14:J14),"") | L14: =IFERROR(G14+K14,"") | S14: =IFERROR(R14/Q14,"")
... G17: =IFERROR(AVERAGE(D17:F17),"") | K17: =IFERROR(AVERAGE(H17:J17),"") | L17: =IFERROR(G17+K17,"") | S17: =IFERROR(R17/Q17,"")
A18: TOTAL / BLENDED | B18: =COUNTA(A3:A17)&" dealers" | D18: =SUM(D3:D17) | E18: =SUM(E3:E17) | F18: =SUM(F3:F17) | G18: =SUM(G3:G17) | H18: =SUM(H3:H17) | I18: =SUM(I3:I17) | J18: =SUM(J3:J17) | K18: =SUM(K3:K17) | ... R18: =SUM(R3:R17) | S18: =IFERROR(R18/Q18,"")

Sheet Summary
A1: DZZLO — Net-Banking Volume Summary for Union Bank of India
A2: Everything below derives from the 'Dealer Data' sheet. Only the yellow / orange cells are typed.
A4: ASSUMPTIONS
B5: Quoted net-banking MDR | C5: 0.018 | D5: The Bank's offer.
B6: Flat fee counter-proposal (₹ per transaction) | C6: 25 | D6: Our ask. Change to test levels.
B7: HSD dealer commission (₹ / litre) | C7: 2.2 | D7: Confirmed — see Topic 2.
B8: HSD pump price (₹ / litre) | D8: CONFIRM. Topic 2 uses ₹93 as a working assumption.
A10: THE DEALER BASE
B11: Dealers in this data set | C11: =COUNTA('Dealer Data'!A3:A17)
B12: Avg monthly MS (petrol) sale — KL | C12: ='Dealer Data'!G18
B13: Avg monthly HSD (diesel) sale — KL | C13: ='Dealer Data'!K18
B14: Avg monthly total throughput — KL | C14: ='Dealer Data'!L18
A16: MONTHLY TRANSACTIONS, ALL DEALERS
B17: Net banking — transactions / month | C17: ='Dealer Data'!Q18
B18: Net banking — value / month | C18: ='Dealer Data'!R18
B19: Net banking — average ticket | C19: =IFERROR(C18/C17,"") | D19: Topic 1/2 claim ~₹1 lakh — this is where the data confirms it.
B20: UPI — transactions / month | C20: ='Dealer Data'!O18
B21: UPI — value / month | C21: ='Dealer Data'!P18
B22: Loyalty / fleet card — transactions / month | C22: ='Dealer Data'!M18
B23: Loyalty / fleet card — value / month | C23: ='Dealer Data'!N18
A25: ANNUALISED — NET BANKING
B26: Transactions / year | C26: =C17*12
B27: Value / year | C27: =C18*12
A29: WHAT THE TWO PRICING MODELS EXTRACT (net banking only)
B30: At the quoted MDR — per month | C30: =C18*C5
B31: At the quoted MDR — per year | C31: =C30*12
B32: At the flat fee — per month | C32: =C17*C6
B33: At the flat fee — per year | C33: =C32*12
B34: MDR ÷ flat fee | C34: =IFERROR(C30/C32,"") | D34: What choosing the wrong axis costs the dealer.
A36: AGAINST THE DEALER'S COMMISSION
B37: Net-banking receipts are credit customers settling diesel bills, so they are measured against HSD commission.
B38: Litres of diesel behind those receipts / month | C38: =IFERROR(C18/C8,"")
B39: Dealer's gross commission on them (₹ / month) | C39: =IFERROR(C38*C7,"")
B40: Quoted MDR as a share of that commission | C40: =IFERROR(C30/C39,"") | D40: Topic 2 puts this near 76%.
B41: Flat fee as a share of that commission | C41: =IFERROR(C32/C39,"")
B43: Note: the MDR share is (MDR × pump price) ÷ commission per litre — it has no volume term in it. It does not improve at scale, and it does not improve at a larger ticket.

Sheet Notes
A1: How to fill this in
B3: Column | C3: What goes in it, and where it comes from
B4: Dealer Name | C4: Outlet / firm name as it appears on the OMC dealership.
B5: Oil Company | C5: IOCL / BPCL / HPCL / Reliance / Nayara / Shell. Dropdown provided.
B6: Trading Area | C6: The dealer's trading area as classified by the OMC.
B7: MS Sale — Month 1/2/3 | C7: Petrol sold, in KILOLITRES, for each of the last three completed months. Source: the dealer's DSR or the OMC dealer portal. If reported in litres, divide by 1,000.
B8: HSD Sale — Month 1/2/3 | C8: Diesel sold, in KILOLITRES, for the same three months. Same source.
B9: Average / Total columns | C9: Computed. Grey and italic — do not type in these.
B10: Loyalty / Fleet Card | C10: Fleet-card business per month (XTRAPOWER, PetroCard / SmartFleet, DriveTrack). Source: the dealer's card terminal reconciliation.
B11: UPI | C11: UPI collections per month. Source: QR / UPI settlement statement.
B12: Net Banking Transfers | C12: Credit customers settling their bills by NEFT / RTGS / IMPS. Source: the dealer's bank statement or receivables ledger. THIS IS THE COLUMN THAT MATTERS — it is the business the IPG would carry.
A14: Four things to get right
B16: Count and value, not just "volume".
B17: Every payment mode is split into transaction COUNT and transaction VALUE, because the whole argument in §3 turns on the difference: the Bank's cost from Easebuzz is driven by the count, and the 1.8% is driven by the value. One number cannot show that. If a dealer can only give one, take the value, estimate the count from a typical ticket, and mark the cell so it is not passed off as observed.
B19: Record which three months these are.
B20: Write the period here → ____________________________ . Use the last three COMPLETED months, the same three for every dealer, and avoid a month distorted by a price change or a supply outage.
B22: This is a projection, not a commitment.
B23: A bank reads any number it is handed as a promise, and a missed promise is how a waiver gets withdrawn. Keep dealers already signed separate from dealers in the pipeline, label the whole thing a projection, and offer the Bank a review at 12 months against actuals.
B25: The Bank can price this without telling us its Easebuzz cost.
B26: We do not know what Easebuzz charges the Bank per net-banking transaction. We do not need to. Handing the Bank the count and the value side by side lets them run their own cost against both axes and see the gap themselves — which is a stronger move than us asserting their margin.
